{
  "restaurant_slug": "fire-lounge",
  "archived_at": "2025-08-16T15:28:59.895367",
  "deals": [
    {
      "title": "Happy Hour",
      "description": "happy hour mon-fri 2:00pm",
      "deal_type": "happy_hour",
      "days_of_week": [],
      "start_time": null,
      "end_time": null,
      "price": null,
      "is_all_day": true,
      "special_notes": [],
      "scraped_at": "2025-08-16T15:28:57.798049",
      "source_url": null,
      "confidence_score": 0.4
    },
    {
      "title": "Happy Hour",
      "description": "happy hour 2pm",
      "deal_type": "happy_hour",
      "days_of_week": [],
      "start_time": null,
      "end_time": null,
      "price": null,
      "is_all_day": true,
      "special_notes": [],
      "scraped_at": "2025-08-16T15:28:57.798065",
      "source_url": null,
      "confidence_score": 0.4
    },
    {
      "title": "Happy Hour",
      "description": "6:30am-10:30am brunch sat-sun 7:00am-2:00pm lunch mon-fri 10:30am-2:00pm bites mon-sun 2:00pm-5:00pm",
      "deal_type": "happy_hour",
      "days_of_week": [],
      "start_time": null,
      "end_time": null,
      "price": null,
      "is_all_day": true,
      "special_notes": [],
      "scraped_at": "2025-08-16T15:28:57.798096",
      "source_url": null,
      "confidence_score": 0.4
    },
    {
      "title": "Time-based Special",
      "description": "6:30AM-10:30AM",
      "deal_type": "happy_hour",
      "days_of_week": [],
      "start_time": null,
      "end_time": null,
      "price": null,
      "is_all_day": true,
      "special_notes": [],
      "scraped_at": "2025-08-16T15:28:57.799165",
      "source_url": null,
      "confidence_score": 0.4
    },
    {
      "title": "Time-based Special",
      "description": "7:00AM-2:00PM",
      "deal_type": "happy_hour",
      "days_of_week": [],
      "start_time": null,
      "end_time": null,
      "price": null,
      "is_all_day": true,
      "special_notes": [],
      "scraped_at": "2025-08-16T15:28:57.799167",
      "source_url": null,
      "confidence_score": 0.4
    },
    {
      "title": "Time-based Special",
      "description": "10:30AM-2:00PM",
      "deal_type": "happy_hour",
      "days_of_week": [],
      "start_time": null,
      "end_time": null,
      "price": null,
      "is_all_day": true,
      "special_notes": [],
      "scraped_at": "2025-08-16T15:28:57.799168",
      "source_url": null,
      "confidence_score": 0.4
    },
    {
      "title": "Time-based Special",
      "description": "2:00PM-5:00PM",
      "deal_type": "happy_hour",
      "days_of_week": [],
      "start_time": null,
      "end_time": null,
      "price": null,
      "is_all_day": true,
      "special_notes": [],
      "scraped_at": "2025-08-16T15:28:57.799168",
      "source_url": null,
      "confidence_score": 0.4
    },
    {
      "title": "Time-based Special",
      "description": "5:00PM-10:00PM",
      "deal_type": "happy_hour",
      "days_of_week": [],
      "start_time": null,
      "end_time": null,
      "price": null,
      "is_all_day": true,
      "special_notes": [],
      "scraped_at": "2025-08-16T15:28:57.799169",
      "source_url": null,
      "confidence_score": 0.4
    }
  ]
}